convert2vars/__init__.py
convert2vars/__main__.py
convert2vars/app/__init__.py
convert2vars/app/app_exception.py
convert2vars/app/app_helper.py
convert2vars/app/app_impl.py
convert2vars/app/constants.py
convert2vars/app/command/__init__.py
convert2vars/app/command/command_convert.py
convert2vars/formatter/__init__.py
convert2vars/formatter/json_formatter.py
convert2vars/formatter/yaml_formatter.py
convert2vars/importer/__init__.py
convert2vars/importer/file_importer.py
convert2vars/parser/__init__.py
convert2vars/parser/ini_parser.py
convert2vars/parser/json_parser.py
convert2vars/parser/parse_helper.py
convert2vars/parser/yaml_parser.py
convert2vars/template/__init__.py
convert2vars/template/template_loader.py
convert2vars/template/template_render.py
convert2vars/util/__init__.py
convert2vars/util/config_util.py
convert2vars/util/logging.py
lib_convert2vars/__init__.py
lib_convert2vars/__main__.py
lib_convert2vars/app/__init__.py
lib_convert2vars/app/app_exception.py
lib_convert2vars/app/app_helper.py
lib_convert2vars/app/app_impl.py
lib_convert2vars/app/constants.py
lib_convert2vars/app/command/__init__.py
lib_convert2vars/app/command/command_convert.py
lib_convert2vars/exporter/__init__.py
lib_convert2vars/exporter/file_exporter.py
lib_convert2vars/formatter/__init__.py
lib_convert2vars/formatter/json_formatter.py
lib_convert2vars/formatter/yaml_formatter.py
lib_convert2vars/importer/__init__.py
lib_convert2vars/importer/file_importer.py
lib_convert2vars/parser/__init__.py
lib_convert2vars/parser/ini_parser.py
lib_convert2vars/parser/json_parser.py
lib_convert2vars/parser/parse_helper.py
lib_convert2vars/parser/yaml_parser.py
lib_convert2vars/template/__init__.py
lib_convert2vars/template/parameter_loader.py
lib_convert2vars/template/parameter_render.py
lib_convert2vars/template/template_loader.py
lib_convert2vars/template/template_render.py
lib_convert2vars/util/__init__.py
lib_convert2vars/util/config_util.py
lib_convert2vars/util/console_util.py
convert2vars-1.0.2.dist-info/LICENSE
convert2vars-1.0.2.dist-info/METADATA
convert2vars-1.0.2.dist-info/WHEEL
convert2vars-1.0.2.dist-info/entry_points.txt
convert2vars-1.0.2.dist-info/top_level.txt
convert2vars-1.0.2.dist-info/RECORD
