Metadata-Version: 2.1
Name: convert2vars
Version: 1.0.2
Summary: A small tool for mutual conversion of JSON, YAML with embedded parameters.
Home-page: https://github.com/t-m0riyama/convert2vars
Author: t-m0riyama
Author-email: 3154232+t-m0riyama@users.noreply.github.com
Classifier: Programming Language :: Python :: 3
Classifier: License :: OSI Approved :: MIT License
Classifier: Operating System :: OS Independent
Classifier: Topic :: Text Processing :: Markup
Requires-Python: >=3.7
License-File: LICENSE
Requires-Dist: click
Requires-Dist: python-dotenv
Requires-Dist: iniconfig
Requires-Dist: Jinja2
Requires-Dist: PyYAML
